nmanifest/__init__.py
nmanifest/generator.py
nmanifest-0.0.2.dist-info/LICENSE
nmanifest-0.0.2.dist-info/METADATA
nmanifest-0.0.2.dist-info/WHEEL
nmanifest-0.0.2.dist-info/top_level.txt
nmanifest-0.0.2.dist-info/RECORD
