Metadata-Version: 2.1
Name: nmanifest
Version: 0.0.2
Summary: Generate dynamic number of manifest repetitions using minimum configuration
Home-page: https://github.com/logiva/nmanifest
Author: Steffen Vinther Sørensen
Author-email: svs@logiva.dk
License: MIT
Platform: UNKNOWN
Classifier: Programming Language :: Python :: 3
Classifier: License :: OSI Approved :: MIT License
Classifier: Operating System :: OS Independent
Requires-Python: >=3.5
Requires-Dist: dict-recursive-update (>=1.0.1)
Requires-Dist: Jinja2 (>=2.10.3)
Requires-Dist: MarkupSafe (>=1.1.1)
Requires-Dist: oyaml (>=0.9)
